[
    {
        "role": "user",
        "content": "Why is the Python string method 'startswith' slower than slicing? Even when including the calculation for length, slicing still appears to be significantly faster. Here is the code and the results I got for timing: \n\n```\nx = 'foobar'\ny = 'foo'\n\n%timeit x.startswith(y)\n# Output: 1000000 loops, best of 3: 321 ns per loop\n\n%timeit x[:3] == y\n# Output: 10000000 loops, best of 3: 164 ns per loop\n\n%timeit x[:len(y)] == y\n# Output: 1000000 loops, best of 3: 251 ns per loop\n```\n\nI also disassembled the bytecode for both the operations and here is the output:\n\n```\nimport dis\ndis_it = lambda x: dis.dis(compile(x, '<none>', 'eval'))\n\ndis_it('x[:3]==y')\n# Output:\n# 1           0 LOAD_NAME                0 (x)\n#             3 LOAD_CONST               0 (3)\n#             6 SLICE+2\n#             7 LOAD_NAME                1 (y)\n#            10 COMPARE_OP               2 (==)\n#            13 RETURN_VALUE\n\ndis_it('x.startswith(y)')\n# Output:\n# 1           0 LOAD_NAME                0 (x)\n#             3 LOAD_ATTR                1 (startswith)\n#             6 LOAD_NAME                2 (y)\n#             9 CALL_FUNCTION            1\n#            12 RETURN_VALUE\n```\n\nCan someone explain why 'startswith' is slower than slicing?"
    },
    {
        "role": "assistant",
        "content": "The difference in performance between using `startswith` and slicing with `==` in Python can be attributed to several factors related to how these operations are implemented and executed internally.\n\n1. **Function Call Overhead**: \n   - The `startswith` method is a function call, which involves more overhead than a simple slice and comparison. Function calls in Python have some inherent overhead due to argument parsing, stack setup, and other function call mechanics.\n   - In the bytecode, you can see that `startswith` involves loading an attribute and then calling a function, which adds to the overhead compared to the direct slice operation.\n\n2. **Method Implementation**:\n   - While `startswith` is optimized in the C implementation of Python (CPython), it still involves some additional checks and operations beyond just comparing the prefix. For example, `startswith` can handle tuples of prefixes, which adds complexity to its implementation.\n   - The slicing operation directly accesses memory and performs a straightforward comparison, which is inherently faster for this specific case.\n\n3. **Generalization vs. Specificity**:\n   - `startswith` is a more general method that provides additional functionality and flexibility, like accepting tuples of prefixes and optional start and end parameters. This generality comes at a cost of additional checks and logic.\n   - Slicing followed by `==` is a specific operation tailored to directly compare the start of a string with another string, making it faster for this particular use case.\n\n4. **Optimizations for Slicing**:\n   - Python\u2019s string slicing is highly optimized, especially for simple cases like slicing from the start of the string. The slicing operation can be executed very efficiently by directly accessing the memory locations of the string.\n\nIn conclusion, while `startswith` is a convenient and powerful method for checking prefixes, its additional features and the inherent overhead of function calls make it slightly slower than the more direct approach of slicing and comparing. If maximum performance is critical and the use case is simple, slicing followed by `==` can be a faster alternative."
    }
]